{
	"cmake" : 
	{
		"generator" : 
		{
			"multiConfig" : false,
			"name" : "Ninja"
		},
		"paths" : 
		{
			"cmake" : "/Users/28rj102230/homebrew/bin/cmake",
			"cpack" : "/Users/28rj102230/homebrew/bin/cpack",
			"ctest" : "/Users/28rj102230/homebrew/bin/ctest",
			"root" : "/Users/28rj102230/homebrew/share/cmake"
		},
		"version" : 
		{
			"isDirty" : false,
			"major" : 4,
			"minor" : 2,
			"patch" : 3,
			"string" : "4.2.3",
			"suffix" : ""
		}
	},
	"objects" : 
	[
		{
			"jsonFile" : "codemodel-v2-8eabc94ce4a5fd0c8a25.json",
			"kind" : "codemodel",
			"version" : 
			{
				"major" : 2,
				"minor" : 9
			}
		},
		{
			"jsonFile" : "cache-v2-3b9947cd6bf3aa4d2a1f.json",
			"kind" : "cache",
			"version" : 
			{
				"major" : 2,
				"minor" : 0
			}
		},
		{
			"jsonFile" : "cmakeFiles-v1-abf71e6affc5837d745b.json",
			"kind" : "cmakeFiles",
			"version" : 
			{
				"major" : 1,
				"minor" : 1
			}
		},
		{
			"jsonFile" : "toolchains-v1-08649ee3c56ed71cf87d.json",
			"kind" : "toolchains",
			"version" : 
			{
				"major" : 1,
				"minor" : 0
			}
		}
	],
	"reply" : 
	{
		"client-vscode" : 
		{
			"query.json" : 
			{
				"requests" : 
				[
					{
						"kind" : "cache",
						"version" : 2
					},
					{
						"kind" : "codemodel",
						"version" : 2
					},
					{
						"kind" : "toolchains",
						"version" : 1
					},
					{
						"kind" : "cmakeFiles",
						"version" : 1
					}
				],
				"responses" : 
				[
					{
						"jsonFile" : "cache-v2-3b9947cd6bf3aa4d2a1f.json",
						"kind" : "cache",
						"version" : 
						{
							"major" : 2,
							"minor" : 0
						}
					},
					{
						"jsonFile" : "codemodel-v2-8eabc94ce4a5fd0c8a25.json",
						"kind" : "codemodel",
						"version" : 
						{
							"major" : 2,
							"minor" : 9
						}
					},
					{
						"jsonFile" : "toolchains-v1-08649ee3c56ed71cf87d.json",
						"kind" : "toolchains",
						"version" : 
						{
							"major" : 1,
							"minor" : 0
						}
					},
					{
						"jsonFile" : "cmakeFiles-v1-abf71e6affc5837d745b.json",
						"kind" : "cmakeFiles",
						"version" : 
						{
							"major" : 1,
							"minor" : 1
						}
					}
				]
			}
		}
	}
}
